riemanifold/__init__.py
riemanifold/examples.py
riemanifold/manifold.py
riemanifold/utils.py
riemanifold-1.1.1.dist-info/METADATA
riemanifold-1.1.1.dist-info/WHEEL
riemanifold-1.1.1.dist-info/licenses/LICENSE
riemanifold-1.1.1.dist-info/RECORD
