Metadata-Version: 2.4
Name: riemanifold
Version: 1.1.1
Summary: A package for performing geometric computations on Riemannian manifolds
Project-URL: Homepage, https://github.com/robert-wbe/RieManifold
Project-URL: Issues, https://github.com/robert-wbe/RieManifold/issues
Author-email: Robert Wiebe <robert.wiebe9@icloud.com>
License: MIT License
License-File: LICENSE
Keywords: Geometry,Manifold,Riemannian
Classifier: Operating System :: OS Independent
Classifier: Programming Language :: Python :: 3
Requires-Python: >=3.10
Requires-Dist: matplotlib>=3.9.2
Requires-Dist: numdifftools>=0.9.41
Requires-Dist: numpy>=1.26.2
Requires-Dist: scipy>=1.14.0
Requires-Dist: torch>=2.3.0
